Metadata-Version: 2.1
Name: RModularity
Version: 0.3.0
Summary: Python library to calculate Robustness modularity of networks
Home-page: https://github.com/filipinascimento/RModularity
Author: Filipi N. Silva
Author-email: filipi@iu.edu
License: UNKNOWN
Platform: UNKNOWN
Classifier: Programming Language :: Python :: 3
Classifier: License :: OSI Approved :: MIT License
Classifier: Operating System :: OS Independent
Requires-Python: >=3.5
